aadishlocalai/__init__.py
aadishlocalai/cli.py
aadishlocalai-0.1.0.dist-info/METADATA
aadishlocalai-0.1.0.dist-info/WHEEL
aadishlocalai-0.1.0.dist-info/entry_points.txt
aadishlocalai-0.1.0.dist-info/top_level.txt
aadishlocalai-0.1.0.dist-info/RECORD
