Metadata-Version: 2.4
Name: aadishlocalai
Version: 0.1.0
Summary: Run ollama commands using 'aadishlocalai' in Windows
Author-email: Aadish Kumar Yadav <your-email@example.com>
Requires-Python: >=3.7
